{"TEAM NAMES":"","Series Number":"369","Filename":"amaka-our-mummy-g.o","Name":"amaka our mummy g.o","Description":"Here's Amaka; our one and only mummy G.O who's been to hell and back.","Gender":"Female","Attributes":{"hair":" dark brown"," eyes":" blue"," teeth":" none"," clothing":" blue v-neck wax print"," accessories":" none"," expression":" none"," strength":" none"," weakness":" none"},"UUID":"853edc40-0f9d-40c5-ba78-46067dfd7f68","Hash":"5184d361a091a17453224519ce61d07ce31800d2d2e43179f20699bf20e8f682"}