{"TEAM NAMES":"","Series Number":"110","Filename":"fayo-the-yorubademon","Name":"fayo the yorubademon","Description":"Fayo is a yoruba demon with excellent communication skills.","Gender":"Male","Attributes":{"hair":" bald"," eyes":" opened"," teeth":" none"," clothing":" africa print"," accessories":" mask"," expression":" none"," strength":" determined"," weakness":" steals"},"UUID":"e270e278-a9b5-408d-b527-d518239a997b","Hash":"fd0541021b85f809097e3c7a4ffd043e1a49dab82be175e955bfb95031f6edf4"}